llm_python.py
llm_python-0.1.dist-info/LICENSE
llm_python-0.1.dist-info/METADATA
llm_python-0.1.dist-info/WHEEL
llm_python-0.1.dist-info/entry_points.txt
llm_python-0.1.dist-info/top_level.txt
llm_python-0.1.dist-info/RECORD
