Metadata-Version: 2.1
Name: llm-python
Version: 0.1
Summary: Run a Python interpreter in the LLM virtual environment
Author: Simon Willison
License: Apache-2.0
Project-URL: Homepage, https://github.com/simonw/llm-python
Project-URL: Changelog, https://github.com/simonw/llm-python/releases
Project-URL: Issues, https://github.com/simonw/llm-python/issues
Project-URL: CI, https://github.com/simonw/llm-python/actions
Classifier: License :: OSI Approved :: Apache Software License
License-File: LICENSE
Requires-Dist: llm
Provides-Extra: test
Requires-Dist: pytest; extra == "test"
